setup.py
Isomap/Isomap.py
Isomap/__init__.py
Isomap/run_script.py
Isomap.egg-info/PKG-INFO
Isomap.egg-info/SOURCES.txt
Isomap.egg-info/dependency_links.txt
Isomap.egg-info/not-zip-safe
Isomap.egg-info/top_level.txt