Metadata-Version: 1.0
Name: Isomap
Version: 1.0
Summary: Deriving faces
Home-page: UNKNOWN
Author: UNKNOWN
Author-email: UNKNOWN
License: UNKNOWN
Platform: UNKNOWN
